lzgym_tool/__init__.py
lzgym_tool/lzgym_tool.py
lzgym_tool-0.0.3.3.dist-info/LICENSE
lzgym_tool-0.0.3.3.dist-info/METADATA
lzgym_tool-0.0.3.3.dist-info/WHEEL
lzgym_tool-0.0.3.3.dist-info/top_level.txt
lzgym_tool-0.0.3.3.dist-info/RECORD
