Metadata-Version: 2.1
Name: lzgym-tool
Version: 0.0.3.3
Summary: LZGYM's Tool
Home-page: https://github.com/jackyli0318/lzgym-tool
Author: Jacky Lee
Author-email: emulezhi@gmail.com
License: UNKNOWN
Platform: UNKNOWN
Classifier: Programming Language :: Python :: 3
Classifier: License :: OSI Approved :: MIT License
Classifier: Operating System :: OS Independent
Requires-Python: >=3.5
